chalice_http_toolkit/__init__.py
chalice_http_toolkit/cloudfront.py
chalice_http_toolkit/content.py
chalice_http_toolkit/multipart.py
chalice_http_toolkit/response_with_binary.py
chalice_http_toolkit/tasking.py
chalice_http_toolkit/version.py
chalice_http_toolkit-0.6.2.data/data/tools/assets/app.py
chalice_http_toolkit-0.6.2.data/data/tools/assets/config.json
tools/chalice_http_toolkit.py
tools/assets/app.py
tools/assets/config.json
chalice_http_toolkit-0.6.2.dist-info/LICENSE.txt
chalice_http_toolkit-0.6.2.dist-info/METADATA
chalice_http_toolkit-0.6.2.dist-info/WHEEL
chalice_http_toolkit-0.6.2.dist-info/entry_points.txt
chalice_http_toolkit-0.6.2.dist-info/top_level.txt
chalice_http_toolkit-0.6.2.dist-info/RECORD
