Metadata-Version: 2.1
Name: chalice-http-toolkit
Version: 0.6.2
Summary: A Flask-like backend toolkit for building & deploying serverless websites directly to AWS Lambda
Home-page: https://gitlab.com/chalice-http-toolkit/chalice-http-toolkit
Author: Chris Lapa
Author-email: 
Project-URL: Bug Tracker, https://gitlab.com/chalice-http-toolkit/chalice-http-toolkit/-/issues
Classifier: Programming Language :: Python :: 3
Classifier: License :: OSI Approved :: GNU Affero General Public License v3 or later (AGPLv3+)
Classifier: Operating System :: OS Independent
Requires-Python: >=3.8
License-File: LICENSE.txt
Requires-Dist: chalice >=1.22.3
Requires-Dist: filetype ==1.2.0
Requires-Dist: requests-toolbelt ==0.9.1
Requires-Dist: pytz ==2021.1
Provides-Extra: layered
Requires-Dist: Jinja2 ==2.10 ; extra == 'layered'
Requires-Dist: Pillow ==8.2.0 ; extra == 'layered'
